UIBoz/UIBoz.py
UIBoz/__init__.py
UIBoz-0.1.dist-info/LICENSE
UIBoz-0.1.dist-info/METADATA
UIBoz-0.1.dist-info/WHEEL
UIBoz-0.1.dist-info/top_level.txt
UIBoz-0.1.dist-info/RECORD
