Metadata-Version: 2.1
Name: UIBoz
Version: 0.1
Summary: Addition to DrawBoz for making UIs
Home-page: https://github.com/ThatAdwaithGuy/DrawBoz
Download-URL: https://github.com/ThatAdwaithGuy
Author: ThatWaiGuy
Author-email: adwaith.3110@gmail.com
License: MIT
Keywords: Boz drawing,Barebones,UI
Classifier: Development Status :: 3 - Alpha
Classifier: Intended Audience :: Developers
Classifier: Topic :: Software Development :: Build Tools
Classifier: License :: OSI Approved :: MIT License
Classifier: Programming Language :: Python :: 3
Classifier: Programming Language :: Python :: 3.4
Classifier: Programming Language :: Python :: 3.5
Classifier: Programming Language :: Python :: 3.6
Classifier: Programming Language :: Python :: 3.11
License-File: LICENSE
